opencensus/__init__.py
opencensus/common/__init__.py
opencensus/common/correlationcontext/__init__.py
opencensus/common/correlationcontext/correlationcontext.py
opencensus_correlation-0.1.0.dist-info/METADATA
opencensus_correlation-0.1.0.dist-info/WHEEL
opencensus_correlation-0.1.0.dist-info/namespace_packages.txt
opencensus_correlation-0.1.0.dist-info/top_level.txt
opencensus_correlation-0.1.0.dist-info/RECORD
