Metadata-Version: 2.1
Name: opencensus-correlation
Version: 0.1.0
Summary: W3C Correlation Context
Home-page: https://github.com/census-instrumentation/opencensus-python/tree/master/contrib/opencensus-correlation
Author: OpenCensus Authors
Author-email: census-developers@googlegroups.com
License: Apache-2.0
Platform: UNKNOWN
Classifier: Intended Audience :: Developers
Classifier: Development Status :: 3 - Alpha
Classifier: Intended Audience :: Developers
Classifier: License :: OSI Approved :: Apache Software License
Classifier: Programming Language :: Python
Classifier: Programming Language :: Python :: 2
Classifier: Programming Language :: Python :: 2.7
Classifier: Programming Language :: Python :: 3
Classifier: Programming Language :: Python :: 3.4
Classifier: Programming Language :: Python :: 3.5
Classifier: Programming Language :: Python :: 3.6
Classifier: Programming Language :: Python :: 3.7
